cip/__init__.py
cip/cip.py
cip/exceptions.py
python_cip-0.0.4.dist-info/DESCRIPTION.rst
python_cip-0.0.4.dist-info/METADATA
python_cip-0.0.4.dist-info/RECORD
python_cip-0.0.4.dist-info/WHEEL
python_cip-0.0.4.dist-info/metadata.json
python_cip-0.0.4.dist-info/top_level.txt
