Metadata-Version: 2.0
Name: python-cip
Version: 0.0.4
Summary: Very simple python interface to Canto Cumulus CIP
Home-page: https://bitbucket.org/fcomuni/python_cip
Author: Fabio Comuni
Author-email: f.comuni@creative-group.it
License: LGPLv2+
Keywords: network
Platform: UNKNOWN
Classifier: Development Status :: 3 - Alpha
Classifier: Intended Audience :: Developers
Classifier: License :: OSI Approved :: GNU Lesser General Public License v2 or later (LGPLv2+)
Requires-Python: >=2.7, <4
Requires-Dist: requests (>=2.12)
